setup.py
shinkenplugins/__init__.py
shinkenplugins.plugins.amt_montreal.egg-info/PKG-INFO
shinkenplugins.plugins.amt_montreal.egg-info/SOURCES.txt
shinkenplugins.plugins.amt_montreal.egg-info/dependency_links.txt
shinkenplugins.plugins.amt_montreal.egg-info/entry_points.txt
shinkenplugins.plugins.amt_montreal.egg-info/namespace_packages.txt
shinkenplugins.plugins.amt_montreal.egg-info/requires.txt
shinkenplugins.plugins.amt_montreal.egg-info/top_level.txt
shinkenplugins/plugins/__init__.py
shinkenplugins/plugins/amt_montreal/__init__.py
shinkenplugins/plugins/amt_montreal/amt_montreal.py
shinkenplugins/plugins/amt_montreal/gtfs_realtime_pb2.py